{
  "task_id": "CRITIC-20260325-284",
  "worker": "critic",
  "status": "success",
  "summary": "Reviewed the inbox runner and its delegate script as an end-to-end readonly smoke pair. Both artifacts are complete, well-structured, and aligned with the best-effort, evidence-backed contract. No critical issues found; the wrapper correctly delegates and validates, and the delegate handles extraction with OCR fallback and clear reporting. Verdict is pass.",
  "artifacts": [
    {
      "path": "artifacts/reviews/pdf_to_excel_ocr_inbox_review.md",
      "type": "review"
    }
  ],
  "timestamp": "2026-03-29T08:50:47.614434Z",
  "duration_ms": 48218,
  "notes": [
    "Static artifact analysis used per runtime evidence policy; live execution not required.",
    "Both wrapper and delegate snapshots reviewed together as per constraints.",
    "All review contract requirements met, including verdict in metadata."
  ],
  "metadata": {
    "task_id": "CRITIC-20260325-284",
    "worker": "critic",
    "verdict": "pass",
    "reviewed_artifacts": [
      "artifacts/scripts/pdf_to_excel_ocr_inbox_runner.py",
      "artifacts/scripts/pdf_to_excel_ocr.py"
    ],
    "verdict_rationale": "Artifacts demonstrate a complete, functional design for readonly PDF-to-Excel smoke with proper error handling, evidence gates, and alignment with best-effort contract. No missing content or critical flaws."
  }
}